{
"type": "FeatureCollection",
"name": "Five Interesting Points at UNC",
"crs": { "type": "name", "properties": { "name": "urn:ogc:def:crs:OGC:1.3:CRS84" } },
"features": [
{ "type": "Feature", "properties": { "id": 1, "notes": "Davis library; students study here, especially during midterms and finals" }, "geometry": { "type": "Point", "coordinates": [ -79.048237568718775, 35.910652251366578 ] } },
{ "type": "Feature", "properties": { "id": 2, "notes": "McCorkle Place; former location of Silent Sam, a Confederate statue that was the site of many protests recently" }, "geometry": { "type": "Point", "coordinates": [ -79.05235070324602, 35.914011843093419 ] } },
{ "type": "Feature", "properties": { "id": 3, "notes": "the Old Well is a symbol of the UNC; people like to take pics and drink water from the fountain for good luck" }, "geometry": { "type": "Point", "coordinates": [ -79.051226306844171, 35.912054149938477 ] } },
{ "type": "Feature", "properties": { "id": 4, "notes": "Student Union; many clubs and organizations meet here and Wendy's is open until 1am in this building" }, "geometry": { "type": "Point", "coordinates": [ -79.04802499691246, 35.910122680163681 ] } },
{ "type": "Feature", "properties": { "id": 5, "notes": "this bus stop links Chapel Hill's transit system to GoTriangle; can go to Southpoint or Raleigh" }, "geometry": { "type": "Point", "coordinates": [ -79.047514994533103, 35.909660685135208 ] } }
]
}
